{"title": "Puff pastry showstoppers", "url": "http://www.bbc.co.uk/food/recipes/puff_pastry_showstoppers_18072", "img": null, "description": "\n    Three sweet treats for the ambitious baker to try. First up is an orange and thyme puff, then a pear, malt and butterscotch millefeuille, finishing with blackberry and lemon verbena cr\u00e8me br\u00fbl\u00e9e custard tarts.Equipment and preparation: you will need a free-standing mixer fitted with a dough hook, 12-hole muffin tin, baking beans and a silicone mat.\n", "prep time": "1-2 hours", "cook time": "1 to 2 hours", "serves": "Makes 36 assorted tarts", "ingredients": [" 30g/1oz white wine vinegar ", " 500g/1lb 2oz plain flour", " 1 tbsp salt", " 400g/14oz unsalted butter", " 50g/1\u00beoz icing sugar, for dusting", " 1 free-range egg, beaten", " 8 free-range egg yolks", " 130g/4\u00bdoz caster sugar", " 20g/\u00beoz cornflour", " 700ml/1\u00bc pint milk", " 50g/1\u00beoz white chocolate, finely chopped", " 1 tbsp chopped fresh thyme", " 1 unwaxed orange, zest only", " 1-2 tsp orange extract", " 200ml/7fl oz double cream, whipped to soft peaks", " 4 sheets gelatine, soaked in water for 10 minutes", " 200ml/7fl oz orange juice", " 2\u00bd sheets gelatine, soaked in water for 10 minutes", " 2-3 tbsp malt extract, to taste", " 100g/3\u00bdoz icing sugar", " 2 tsp dried powdered malt", " 2 pears (such as Williams or Rocha), ripe but still firm, peeled and sliced 1cm/\u00bdin thick", " 80g/3oz unsalted butter, softened", " 40g/1\u00bdoz brown sugar", " 100g/3\u00bdoz plain flour", " 1 tsp finely chopped fresh lemon thyme", " 50g/1\u00beoz unsalted butter", " 50g/1\u00beoz soft brown sugar", " 25g/1oz barley malt syrup ", " 25g/1oz golden syrup ", " 1 vanilla pod, split in half lengthways", " \u00bd lemon, juice only", " 80ml/2\u00bdfl oz double cream", " 700ml/1\u00bc pint milk", " 2 tbsp dried lemon verbena", " 8 free-range egg yolks", " 130g/4\u00bdoz caster sugar", " 20g/1oz cornflour", " 1 lemon, zest and juice", " 1-2 tsp lemon extract", " 100g/3\u00bdoz caster sugar", " 12 fresh lemon verbena leaves ", " 12 blackberries"]}