{"title": "Slow roast pork shoulder with roasted vegetable tabbouleh and apple BBQ sauce", "url": "http://www.bbc.co.uk/food/recipes/slow_roast_pork_shoulder_08225", "img": null, "description": "\n    This recipe for meltingly tender pork is a great alternative to a Sunday roast. You can even make the tabbouleh and apple sauce in advance and serve them at room temperature.\n", "prep time": "less than 30 mins", "cook time": "over 2 hours", "serves": "Serves 4", "ingredients": [" 3.5kg/7lb 10oz boned pork shoulder, skin scored", " 2 courgettes, thinly sliced", " 1 aubergine, thinly sliced", " 1 red pepper, cut into quarters, seeds removed", " 2 red onions, cut into wedges", " 4 tbsp olive oil", " 250g/9oz bulgur wheat, soaked in cold water overnight", " 1 bunch fresh mint, roughly chopped", " 1 bunch fresh coriander, roughly chopped", " 2 lemon, juice only", " 1 pomegranate, seeds only", " 6 tbsp extra virgin olive oil", " 1 tbsp olive oil", " 1 onion, finely chopped", " 2 garlic cloves, finely chopped", " 2 Bramley apples, peeled, roughly chopped", " 1 red chilli, finely chopped", " 50g/2oz dark muscavado sugar", " 50ml/2fl oz teriyaki sauce", " 2 tbsp cider vinegar", " 150ml/5fl oz tomato ketchup"]}