{"title": "Honey and sesame chicken skewers with griddled squash and spicy curly kale", "url": "http://www.bbc.co.uk/food/recipes/honeyandsesamechicke_82108", "img": null, "description": null, "prep time": "less than 30 mins", "cook time": "10 to 30 mins", "serves": "Serves 2", "ingredients": [" 1 chicken breast, skinned and cut into 1in cubes", " salt and freshly ground black pepper", " 1 tbsp honey", " 1\u00bd tbsp sesame seeds", " 1 tbsp olive oil", " 1 tbsp olive oil", " \u00bd butternut squash, par-boiled for 5 minutes and drained", " salt and freshly ground black pepper", " 1 tbsp olive oil", " 3 spring onions, finely chopped", " 125g/4\u00bdoz curly kale, chopped", " 3tbsp white wine", " 1 tbsp dried chilli flakes", " salt and freshly ground black pepper"]}