{"title": "Creamy pasta with cherry tomato and prosciutto", "url": "http://www.bbc.co.uk/food/recipes/penneprosciuttonestw_88842", "img": null, "description": "\n     A little wine, cream and prosciutto make a quick pasta dinner that feels like a treat. Serve with lots of salad.\n", "prep time": "less than 30 mins", "cook time": "10 to 30 mins", "serves": "Serves 2", "ingredients": [" 1 tbsp olive oil", " 55g/2oz fresh peas", " 6 cherry tomatoes, halved", " 2 tbsp white wine", " 100ml/3\u00bdfl oz double cream", " salt and freshly ground black pepper", " 150g/5\u00bdoz penne pasta, cooked according to packet instructions", " 4 slices prosciutto"]}