{"title": "Tagliatelle with mussels", "url": "http://www.bbc.co.uk/food/recipes/tagliatelle_with_mussels_64767", "img": null, "description": "\n    Gennaro Contaldo's simple sauce is made extra-special with homemade pasta. Use shop-bought pasta for a quicker supper.\n", "prep time": "30 mins to 1 hour", "cook time": "less than 10 mins", "serves": "Serves 4", "ingredients": [" 150g/5oz Italian \u201800\u2019 flour, plus extra for flouring", " 50g/2oz semolina, plus extra for dusting", " 2 free-range eggs", " 6 tbsp extra virgin olive oil", " 1 anchovy fillet, finely chopped", " 1 tbsp capers, finely chopped", " 3 garlic cloves, finely chopped", " 1 x 400g/14oz tin plum tomatoes, chopped", " \u00bd tsp dried oregano", " \u00bc red chilli, finely chopped", " 800g/1lb 12oz mussels, cleaned and de-bearded (discard any mussels that do not close tightly when tapped)", " handful fresh parsley, finely chopped", " salt"]}