{"title": "Mini beef Wellingtons", "url": "http://www.bbc.co.uk/food/recipes/mini_beef_wellingtons_53236", "img": null, "description": "\n    These individual beef Wellingtons can either be served hot as a main course with veggies, or cold as a picnic treat.\n", "prep time": "30 mins to 1 hour", "cook time": "30 mins to 1 hour", "serves": "Makes 6 individual beef Wellingtons", "ingredients": [" 100g/3\u00bdoz salted butter, cut into cubes and frozen", " 100g/3\u00bdoz lard, cut into cubes and frozen", " 250g/9oz plain flour", " \u00bd tsp salt", " 1 tbsp lemon juice", " garlic infused oil (available from most large supermarkets), for frying", " 2 cloves smoked garlic, finely chopped", " 1 shallot, finely chopped", " 10g dried porcini mushrooms, soaked in boiling water for a few minutes", " 125g/4\u00bdoz chestnut mushrooms, washed, sliced ", " small bunch of thyme", " 50ml/2fl oz dry white wine", " 1 tsp sea salt", " cracked black pepper", " 6 x 80g/3oz pieces fillet steak", " salt and freshly ground black pepper", " 6 slices prosciutto ham", " 1 free-range egg, beaten"]}