{"title": "Pork shoulder steaks and beetroot 'pilau'", "url": "http://www.bbc.co.uk/food/recipes/porkshouldersteaksan_79741", "img": null, "description": null, "prep time": "less than 30 mins", "cook time": "1 to 2 hours", "serves": "Serves 4", "ingredients": [" 4 thick cut pork shoulder steaks", " salt and freshly ground black pepper", " plain flour", " 1 tbsp olive oil", " 2 tsp caraway seeds", " 350ml/12fl oz chicken stock", " 250ml/9fl oz cider or white wine", " 1 bay leaf", " 1 tbsp unsalted butter", " 500g/1lb beetroot, peeled and roughly chopped", " 1 medium shallot, peeled and roughly chopped", " 1 clove garlic, peeled and roughly chopped", " 500ml/1pt chicken or vegetable stock", " 10-12 black peppercorns", " 1 tsp caster sugar", " salt ", " 25g/1oz unsalted butter", " 100g/3\u00c2\u00bdoz soured cream ", " 2 sprigs fresh dill, finely chopped"]}