{"title": "Pheasant simmered in milk, cream and celeriac", "url": "http://www.bbc.co.uk/food/recipes/pheasant_simmered_in_48387", "img": null, "description": "\n    This is such an easy and delicious way to roast a pheasant. Just serve with simple green veg.\n", "prep time": "less than 30 mins", "cook time": "30 mins to 1 hour", "serves": "Serves 2", "ingredients": [" 1 ready-to-roast pheasant (about 1kg/2lb 4oz) ", " 1 sprig rosemary", " 4 slices pancetta", " 1 small celeriac, peeled and cut into 1cm/\u00bdin cubes", " 2 tbsp extra virgin olive oil", " 2 tbsp dry Marsala wine", " 300ml/10fl oz milk", " 50ml/2fl oz double cream", " 1 garlic clove, sliced ", " sea salt and freshly ground black pepper"]}