{"title": "Brown shrimp tartlets", "url": "http://www.bbc.co.uk/food/recipes/brown_shrimp_tartlets_80711", "img": null, "description": "\n    The poshest quiche ever - sweet brown shrimps with samphire and blue cheese, encased in crisp filo pastry. \n", "prep time": "30 mins to 1 hour", "cook time": "10 to 30 mins", "serves": "Serves 8", "ingredients": [" 4 sheets filo pastry", " 50g/1\u00beoz clarified butter ", " 3 free-range eggs", " 2 free-range egg yolks", " 425ml/\u00be pint double cream ", " pinch freshly grated nutmeg", " salt and freshly ground black pepper", " 2 tbsp rapeseed oil or olive oil", " 2 bunches spring onions, finely sliced", " few sprigs samphire", " 100g/3\u00bdoz peeled brown shrimps", " 40g/1\u00bdoz blue cheese, freshly grated"]}