{"title": "Roast heritage carrots with garlic scapes and fresh almonds", "url": "http://www.bbc.co.uk/food/recipes/roast_heritage_carrots_00247", "img": null, "description": "\n    Garlic scapes are the stalks of garlic plants. They have a very distinctive flavour, similar to wild garlic. This colourful dish celebrates the best of British seasonal ingredients.\n", "prep time": "less than 30 mins", "cook time": "10 to 30 mins", "serves": "Serves 2", "ingredients": [" 6 heritage carrots, preferably in red, yellow and orange, with the green tops still intact, peeled and washed ", " 2 carrots, roughly chopped", " rapeseed oil, for drizzling", " 60g/2\u00bcoz butter", " 1 bunch garlic scapes, sliced", " 100g/3\u00bdoz fresh green almonds, cracked and peeled", " 1 lemon, juice only", " salt and freshly ground black pepper"]}