{"title": "style sea bass", "url": "http://www.bbc.co.uk/food/recipes/thaistyleseabass_78365", "img": null, "description": null, "prep time": "less than 30 mins", "cook time": "10 to 30 mins", "serves": "Serves 1", "ingredients": [" 1 tbsp olive oil", " 1 sea bass fillet ", " 100g/4oz Thai fragrant rice, cooked according to packet instructions, kept warm", " 3 shallots, sliced and fried", " \u00c2\u00bd chilli, chopped", " handful fresh coriander, chopped", " 1 tbsp water", " 150g/5oz spinach, washed and chopped", " salt and freshly ground black pepper", " 1 tbsp soy sauce", " 1 tsp sesame oil", " 1 tsp chilli, chopped", " juice of 1 lime"]}