{"title": "St. Clements orange and lemon drizzle cake", "url": "http://www.bbc.co.uk/food/recipes/st_clements_orange_and_78030", "img": "http://ichef.bbci.co.uk/food/ic/food_16x9_608/recipes/st_clements_orange_and_78030_16x9.jpg", "description": "\n    My dad was always very proud of his London roots and so as a tribute to him, I\u2019ve made this cake in homage to the famous bells of St. Clements.For this recipe you will need 2 x 23cm/9in springform cake tins and an electric mixer.\n", "prep time": "1-2 hours", "cook time": "1 to 2 hours", "serves": "Makes 1 large cake", "ingredients": [" 450g/1lb caster sugar", " 450g/1lb unsalted butter, allow extra for greasing (at room temperature)", " 4 lemons, zest only", " 8 large free-range eggs, beaten", " 450g/1lb self-raising flour", " 6 large free-range egg yolks", " 175g/6oz caster sugar", " 4 large oranges, zest and 300ml/10fl oz juice only", " squeeze fresh lemon juice", " 110g/4oz unsalted butter, cubed", " 6 lemons, juice only (reserve the peel of 1 lemon)", " 75g/2\u00bdoz caster sugar", " 1 orange, peel only ", " 1 lemon, peel only (see above)", " 200g/7oz caster sugar, plus extra for sprinkling", " 300g/10\u00bdoz icing sugar", " 3-5 tbsp lemon juice"]}