{"title": "Cheesy salmon and spaghetti bake", "url": "http://www.bbc.co.uk/food/recipes/cheesysalmonandspagh_83965", "img": null, "description": null, "prep time": "less than 30 mins", "cook time": "10 to 30 mins", "serves": "Serves 2", "ingredients": [" 200ml/7fl oz double cream", " sea salt and freshly ground black pepper", " 110g/4oz skinless salmon fillet, chopped", " handful fresh flatleaf parsley, chopped", " 55g/2oz parmesan cheese, grated plus a handful extra to sprinkle", " 200g/7oz spaghetti, cooked according to packet instructions", " fresh chives, chopped, to garnish"]}