{"title": "Beef fillet with chicory and blue cheese salad and celeriac chips", "url": "http://www.bbc.co.uk/food/recipes/beef_fillet_on_the_bone_66102", "img": null, "description": "\n    The rich, creamy walnuts complement the crisp and crunchy side salad in this delicious steak supper.Equipment: You will need a food processor.\n", "prep time": "30 mins to 1 hour", "cook time": "1 to 2 hours", "serves": "Serves 2", "ingredients": [" 100g/3\u00bdoz egg white (3 small free-range eggs whites)", " 500g-1kg/1lb 2oz-2lb 4oz fine salt", " 1 celeriac, approx 650g/1lb 7oz", " 390g jar pickled walnuts", " 100g/3\u00bdoz tapioca flour", " vegetable oil, for deep-frying", " olive oil, for frying", " 1 fillet of beef on the bone ", " 1 red chicory", " 1 white chicory", " 1 fris\u00e9e lettuce", " 75g/2\u00beoz of blue cheese, crumbled", " 1 tbsp 2.5cm/1in chopped chives", " 2 tbsp walnut oil, for drizzling", " salt and freshly ground black pepper ", " 300ml/10fl oz jus or beef gravy, to serve", " 2 walnuts, roughly chopped, to serve"]}