{"title": "Baklava with rose, cardamom and pistachio or orange, cinnamon, walnut and almond", "url": "http://www.bbc.co.uk/food/recipes/rose_cardamom_and_45563", "img": null, "description": "\n    Two flavours and shapes of baklava for your delectation. Make one for an after dinner treat or both for a feast.\n", "prep time": "less than 30 mins", "cook time": "30 mins to 1 hour", "serves": "Serves 10", "ingredients": [" 225g/8oz granulated sugar", " 2 tbsp clear honey", " 1 tsp lemon juice", " 1 tbsp rose essence (or 2 tbsp rosewater)", " 200g/7oz shelled pistachios ", " 75g/2\u00bdoz icing sugar", " \u00bd tbsp ground cardamom ", " 6 sheets ready-made filo pastry", " 75g/2\u00bdoz butter, melted, plus extra for greasing", " 225g8oz caster sugar", " 2 tbsp clear honey", " 1 tsp lemon juice", " 1 tbsp orange essence", " 100g/3\u00bdoz walnuts", " 100g/3\u00bdoz almonds", " 75g/2\u00bdoz icing sugar", " 1 tsp ground cinnamon", " 1 orange, zest only", " 3 tbsp crystallised ginger, finely chopped", " 6 sheets ready-made filo pastry", " 75g/2\u00bdoz butter, melted "]}