{"title": "Spaghetti vongole", "url": "http://www.bbc.co.uk/food/recipes/spaghettivongole_88988", "img": "http://ichef.bbci.co.uk/food/ic/food_16x9_608/recipes/spaghettivongole_88988_16x9.jpg", "description": "\n    Anchovy paste is a revelation - so useful for adding that little touch of savoury flavour to simple pasta dishes like this.\n", "prep time": "less than 30 mins", "cook time": "10 to 30 mins", "serves": "Serves 4", "ingredients": [" 500g/1lb very small fresh clams, or a small jar of clams in brine", " 3 tbsp olive oil", " 2 garlic cloves, finely chopped", " 1 tsp anchovy paste", " 2 tbsp finely chopped parsley", " 400g/14oz canned chopped tomatoes", " salt and freshly ground black pepper", " 450g/1lb dried spaghetti"]}