{"title": "Strawberry and clotted cream summer puddings", "url": "http://www.bbc.co.uk/food/recipes/strawberry_and_clotted_77424", "img": "http://ichef.bbci.co.uk/food/ic/food_16x9_608/recipes/strawberry_and_clotted_77424_16x9.jpg", "description": "\n    Individual summer puddings ready in less than 30 minutes - no overnight chilling required. \n", "prep time": "less than 30 mins", "cook time": "10 to 30 mins", "serves": "Serves 2", "ingredients": [" 500g/1lb 2oz fresh strawberries, hulled and halved", " 1 tbsp finely shredded basil", " vegetable oil, for greasing", " 6 slices thin white bread", " 4 tbsp clotted cream", " 4 strawberries, halved, for decoration", " 50ml/2fl oz double cream", " 100g/3\u00bdoz caster sugar"]}