{"title": "Saddle of lamb with herb crust and dauphinoise potato", "url": "http://www.bbc.co.uk/food/recipes/saddle_of_lamb_with_herb_91234", "img": null, "description": "\n    This easy lamb recipe is served with a hearty potato bake, glazed fennel and sweet squashy cherry tomatoes.\n", "prep time": "30 mins to 1 hour", "cook time": "1 to 2 hours", "serves": "Serves 4", "ingredients": [" 150ml/5fl oz double cream", " 150ml/5fl oz full-fat milk", " 2 garlic cloves, crushed", " salt and freshly ground black pepper", " knob of butter, for greasing", " 1kg/2lb 4oz waxy potatoes, such as Desiree, sliced thinly", " dash olive oil", " about 900g/2lb boneless saddle of lamb, rolled and held with string (you can get your butcher to do this)", " 200g/7oz breadcrumbs", " 1 bunch fresh thyme, chopped", " 1 bunch fresh flat-leaf parlsey, chopped", " 1 tbsp Dijon mustard", " 1 head of fennel", " 1 ladle chicken stock", " 2 tbsp olive oil", " 1 tbsp balsmic vinegar", " 1 tsp sugar", " 4 cherry tomatoes, skinned", " 6 sprigs fresh thyme"]}