{"title": "French chicken with new potatoes", "url": "http://www.bbc.co.uk/food/recipes/frenchchickenwithnew_76870", "img": null, "description": null, "prep time": "less than 30 mins", "cook time": "10 to 30 mins", "serves": "Serves 1", "ingredients": [" \u00bd poussin ", " 4 tbsp butter ", " \u00bd onion, sliced", " 3 tbsp fresh tarragon, chopped", " 1 tbsp fresh rosemary leaves, chopped", " 5 tbsp white wine ", " 70ml/2\u00bdfl oz double cream", " 150g/5\u00bcoz cooked new potatoes", " 3 tbsp butter, melted ", " salt and freshly ground black pepper"]}