{"title": "Minced beef pinwheels", "url": "http://www.bbc.co.uk/food/recipes/minced_beef_pinwheels_78308", "img": "http://ichef.bbci.co.uk/food/ic/food_16x9_608/recipes/minced_beef_pinwheels_78308_16x9.jpg", "description": "\n    Great finger food for a picnic or drinks party, these pinwheels are tasty when still warm from the oven. \n", "prep time": "less than 30 mins", "cook time": "30 mins to 1 hour", "serves": "Makes 12", "ingredients": [" 1 tbsp sunflower oil", " \u00bd medium onion, peeled and finely chopped", " 1 garlic clove, crushed", " 500g lean beef mince", " 1 tsp dried mixed herbs", " 1 tbsp tomato pur\u00e9e", " 1 tbsp plain flour, plus extra for rolling", " 500g block of ready-made puff pastry", " 50g mature Cheddar, finely grated (optional)", " 1 medium egg, beaten", " salt and freshly ground black pepper"]}