{"title": "Italian sausage, broad beans and peas", "url": "http://www.bbc.co.uk/food/recipes/italian_sausage_broad_76643", "img": null, "description": "\n    You'll need to take a trip to an Italian deli for the ingredients, but once the shopping\u2019s done this hearty recipe really couldn\u2019t be easier. \n", "prep time": "less than 30 mins", "cook time": "10 to 30 mins", "serves": "Serves 4", "ingredients": [" 2 tbsp extra virgin olive oil", " 50g/1\u00beoz red onions or spring onions, roughly chopped", " 120g/4\u00bcoz soft, spicy Calabrian or Tuscan sausage (or a very soft cooking chorizo), skin removed, meat crumbled ", " 50ml/2fl oz Marsala wine", " 120g/4\u00bcoz broad beans, shelled ", " 120g/4\u00bcoz peas, shelled ", " 1 handful basil, roughly chopped ", " 1 handful flatleaf parsley, roughly chopped ", " 1 handful mint leaves, roughly chopped", " 30g/1oz Sardinian ricotta mustia (available from Italian delicatessens) or a similar salted, lightly smoked soft cheese or a soft goats\u2019 cheese", " 1 handful pea shoots", " pinch black fennel seeds", " sea salt and freshly ground black pepper"]}