{"title": "Smoked salmon and potato quiche", "url": "http://www.bbc.co.uk/food/recipes/smokedsalmonandpotat_90568", "img": "http://ichef.bbci.co.uk/food/ic/food_16x9_608/recipes/smokedsalmonandpotat_90568_16x9.jpg", "description": "\n    This hearty salmon and potato quiche is perfectly portable for picnics and lunchboxes.\n", "prep time": "less than 30 mins", "cook time": "30 mins to 1 hour", "serves": "Serves 8", "ingredients": [" 225g/8oz ready-made shortcrust pastry", " 1 free-range egg, beaten", " 175g/6oz smoked salmon, chopped", " 100g/3\u00bdoz smoked bacon lardons, cooked", " 100g/3\u00bd new potatoes, cooked and cut into cubes", " 3 free-range eggs", " 1 tbsp finely chopped fresh dill", " 200ml/7fl oz cr\u00e8me fra\u00eeche", " 1 tsp grated nutmeg ", " salt and freshly ground black pepper", " green salad leaves, to serve"]}