{"title": "fried sea bass on a red risotto with roasted cherry tomatoes", "url": "http://www.bbc.co.uk/food/recipes/panfriedseabassonare_87954", "img": null, "description": null, "prep time": "less than 30 mins", "cook time": "10 to 30 mins", "serves": "Serves 1", "ingredients": [" 150g/5\u00bdoz sea bass fillet", " dash olive oil", " salt and freshly ground black pepper", " dash olive oil", " \u00bd onion, finely chopped", " 1 garlic clove, finely chopped", " 30g/1oz chorizo, chopped", " 200g/7oz basmati rice, boiled for five minutes, then drained", " pinch ground turmeric", " 1 tsp tomato pur\u00e9e", " 100ml/3\u00bdfl oz white wine", " dash Tabasco sauce", " 1 small bunch cherry tomatoes on the vine", " dash olive oil", " salt and freshly ground black pepper"]}