{"title": "cup pudding with butterscotch sauce", "url": "http://www.bbc.co.uk/food/recipes/sevencuppuddingwithb_87487", "img": null, "description": "\n    Non-Scots might eat this with some custard or cream, but I would inundate it with custard, cream - and (don't forget that sweet tooth of ours!) a scoop of best-quality ice-cream.\n", "prep time": "less than 30 mins", "cook time": "over 2 hours", "serves": "Serves 6", "ingredients": [" 1 mug raisins", " 1 mug sultanas", " 1 mug self-raising flour", " 1 mug shredded suet", " 1 mug fresh breadcrumbs", " 1 mug light muscovado sugar", " 1 level tsp ground cinnamon", " 1 heaped tsp ground mixed spice", " 1 mug whole milk", " 1 medium free-range egg, beaten", " butter, for greasing", " 75g/2\u00beoz light muscovado sugar", " 50g/2oz butter", " 150ml/5fl oz double cream", " few drops vanilla extract", " cr\u00e8me fra\u00eeche, to serve"]}