{"title": "Pork and butter bean stew", "url": "http://www.bbc.co.uk/food/recipes/porkandbutterbeanste_72960", "img": null, "description": null, "prep time": "overnight", "cook time": "over 2 hours", "serves": "Serves 6", "ingredients": [" 50g/2oz butter", " 1 tbsp garlic pur\u00e9e", " 2 tsp sweet paprika", " 2 tsp caraway seeds", " 255g/9oz belly pork, boned and cubed", " 85ml/3fl oz dry white wine", " 255g/9oz butter beans (soaked overnight)", " 1 litre/1\u00be pints water", " flatleaf parsley, to garnish", " crusty white bread, to serve"]}