{"title": "Surf and turf with wilted spinach, watercress and a mustard sauce", "url": "http://www.bbc.co.uk/food/recipes/surf_and_turf_with_46844", "img": null, "description": "\n    Enjoy a full house with surf and turf \u2013 a sure-fire recipe for a memorable meal.\n", "prep time": "less than 30 mins", "cook time": "10 to 30 mins", "serves": "Serves 4", "ingredients": [" 2 x 500g/1lbs 2oz cooked lobsters", " 4 x 175g/6oz fillet steaks", " 75g/3oz butter", " 2 tbsp olive oil", " 1 lemon, juice only", " 250g/9oz spinach", " 250g/9oz watercress, leaves picked", " 50g/2oz butter", " 2 shallots, finely diced", " 150ml/5fl oz white wine", " 300ml/10fl oz double cream", " 2 tbsp grain mustard", " 2 tomatoes, skinned, deseeded, chopped", " 2 tbsp chives, finely chopped"]}