{"title": "Fruity prize pie", "url": "http://www.bbc.co.uk/food/recipes/fruity_prize_pie_78823", "img": null, "description": "\n    Kids under five can cook this easy fruit pie. You can also use blueberries, blackberries or ripe peaches.\n", "prep time": "less than 30 mins", "cook time": "10 to 30 mins", "serves": "Serves 2", "ingredients": [" 125g/5oz shortcrust pastry", " plain flour", " 2 heaped tsp rolled oats", " 140g/5oz fresh cherries", " 2 heaped tbsp demerara sugar ", " pinch of cinnamon "]}