{"title": "Caponata", "url": "http://www.bbc.co.uk/food/recipes/caponata_82903", "img": null, "description": null, "prep time": "30 mins to 1 hour", "cook time": "30 mins to 1 hour", "serves": "Serves 4", "ingredients": [" 4 medium aubergines, chopped", " salt and freshly ground black pepper", " 3-4 tbsp extra virgin olive oil, plus extra for drizzling", " 1 onion, chopped", " 2 celery sticks, chopped", " 400g/14oz chopped tomatoes", " 100g/3\u00bdoz green olives, pitted and sliced", " 3 tbsp capers, drained and chopped", " 30ml/1fl oz red wine vinegar", " 1\u00bd tbsp sugar, or to taste", " handful flatleaf parsley, chopped", " extra virgin olive oil, for drizzling"]}