{"title": "Prawn linguine with chorizo and tomato sauce", "url": "http://www.bbc.co.uk/food/recipes/prawn_linguine_with_14078", "img": null, "description": "\n    Add some style to your pasta supper with this simple recipe. \n", "prep time": "less than 30 mins", "cook time": "10 to 30 mins", "serves": "Serves 4", "ingredients": [" 2 tsp fennel seeds, slightly crushed in a pestle and mortar", " 150g/5\u00bdoz spicy chorizo ring", " 2 sprigs fresh rosemary, leaves only, finely chopped", " 2 garlic cloves, finely chopped", " 1 red chilli, seeds removed and finely chopped", " olive oil", " 2 x 400g tins chopped tomatoes", " 1 glass of Cabernet Sauvignon, about 150ml/5fl oz or other red wine or a good fish or chicken stock", " 1 tbsp harissa paste, or tomato pur\u00e9e if you don\u2019t like it too hot", " 2 tsp dried oregano", " 300g/10\u00bdoz linguine pasta", " 125g/4\u00bdoz prawns, peeled (preferably raw but cooked will work too)", " 200g mussels, scrubbed and de-bearded", " 2 tsp caster sugar (optional)", " small handful of fresh flat leaf parsley, to serve", " salt and freshly ground black pepper"]}