{"title": "Carrot and courgette muffins", "url": "http://www.bbc.co.uk/food/recipes/carrot_and_courgette_63594", "img": "http://ichef.bbci.co.uk/food/ic/food_16x9_608/recipes/carrot_and_courgette_63594_16x9.jpg", "description": "\n    These moist, yummy muffins are packed with goodness and are perfect for the kids' lunchboxes.\n", "prep time": "less than 30 mins", "cook time": "10 to 30 mins", "serves": "Makes 9", "ingredients": [" 1 free-range egg", " \u00bc courgette (about 20g/\u00beoz), trimmed, grated", " \u00bc carrot (about 20g/\u00beoz), peeled, grated", " 1 heaped tbsp raisins", " 2 tbsp milk", " 1 tbsp sunflower oil", " 75g/3oz plain flour", " 15g/\u00bdoz light soft brown sugar", " 1 tsp baking powder"]}