{"title": "Roxy's caramelised fruits with a Grand Marnier cream", "url": "http://www.bbc.co.uk/food/recipes/roxyscaramelisedfrui_73261", "img": null, "description": null, "prep time": "less than 30 mins", "cook time": "less than 10 mins", "serves": "Serves 2", "ingredients": [" 50g/2oz butter", " 100g/3\u00bdoz brown sugar", " 4 ripe plums, halved and stoned", " 2 ripe Conference pears, sliced", " 2 Cox apples, cored and sliced", " 227g/8\u00bcoz tub clotted cream", " 2 tsp Grand Marnier", " \u00bd orange, zest only"]}