{"title": "Salmon ravioli", "url": "http://www.bbc.co.uk/food/recipes/salmonravioli_86709", "img": null, "description": "\n    Equipment: You'll need a pasta machine for this recipe.\n", "prep time": "30 mins to 1 hour", "cook time": "less than 10 mins", "serves": "Serves 4", "ingredients": [" 100g/3\u00bdoz king scallop meat or 2-3 king scallops, removed from their shells and cleaned", " 100ml/3\u00bdfl oz double cream", " 600g/1lb 5oz salmon fillet, skinned and chopped", " Few fresh coriander leaves, chopped", " few fresh basil leaves, chopped", " squeeze of lemon juice", " 1 tbsp soy sauce", " 4 tbsp sesame oil (not toasted sesame oil)", " 2 tbsp balsamic vinegar", " 2.5cm/1in piece fresh ginger, peeled and sliced", " salt and freshly ground black pepper", " 500g/1lb 1\u00bdoz fresh pasta dough", " 1 free-range egg, beaten", " splash olive oil ", " 1 tbsp olive oil", " 150g/5\u00bcoz spinach leaves", " salt and freshly ground black pepper", " 1-2 sprigs fresh basil, leaves torn", " 1 sprig fresh dill, chopped", " 1 sprig fresh flatleaf parsley, chopped", " 3-4 pinches micro-cresses (optional), available from some supermarkets"]}