{"title": "Picnic of piccalilli, ham, anchovy dip and pork pies", "url": "http://www.bbc.co.uk/food/recipes/picnicofpiccalilliha_86566", "img": null, "description": null, "prep time": "overnight", "cook time": "over 2 hours", "serves": "Serves 4-6", "ingredients": [" 125g/4\u00bdoz table salt", " 2 litres/3\u00bd pints water", " 300g/11oz cauliflower florets", " 225g/8oz baby onions, peeled", " 225g/8oz cucumber, seeds removed, cut into large chunks", " 2 tsp capers, rinsed and drained", " 60g/2\u00bdoz butter", " 4 tbsp flour", " 200ml/7fl oz malt vinegar", " 200ml/7fl oz white wine vinegar", " 50g/2oz caster sugar", " 2 tsp ground turmeric", " 1\u00bc tsp mustard powder", " freshly ground black pepper", " 1kg/2.2lb raw gammon", " 1 onion, cut into quarters", " 4 cloves", " 2 bay leaves", " 2 sprigs fresh thyme", " 2 sprigs fresh flatleaf parsley", " 4 canned anchovies, drained", " 1 lemon, zest only", " 1 garlic clove, peeled", " 4 tbsp double cream", " 75ml/3fl oz extra virgin olive oil", " salt and freshly ground black pepper ", " 250g/8\u00beoz mature cheddar", " 4 ready-made pork pies", " 1 cauliflower, cut into florets", " 1 bunch baby carrots, washed and trimmed", " 200g/7oz ripe cherry tomatoes"]}