{"title": "Hot and sour chicken", "url": "http://www.bbc.co.uk/food/recipes/hot_and_sour_chicken_08241", "img": null, "description": "\n    Sticky rice and courgette noodles make this simple stir-fry really special. \n", "prep time": "30 mins to 1 hour", "cook time": "10 to 30 mins", "serves": "Serves 4", "ingredients": [" 350g/12oz premium grade sushi rice, washed well and rinsed in cold water until the water runs clear", " 2 medium red chillies, seeds removed and sliced", " 4 garlic cloves, finely chopped", " 1 tbsp chilli bean paste ", " 1 tbsp tamari", " 2 tbsp rice vinegar", " 4 tbsp organic honey", " 1 tbsp groundnut oil", " 1 garlic clove, finely chopped", " 2.5cm/1in piece fresh root ginger, peeled and sliced into matchsticks", " 4 large chicken thighs, skin off, de-boned, and sliced into 1cm/\u00bdin cubes", " 1 tbsp Shaoxing rice wine, or dry sherry ", " 2 large courgettes, sliced into long, thin strips sliced using a peeler", " 1 garlic clove, finely chopped", " 1 tsp grated root ginger", " 1 medium red chilli, seeds removed and finely chopped", " 1 tsp tamari ", " 1 tsp Chinkiang black rice vinegar or balsamic vinegar ", " \u00bd tbsp toasted sesame oil", " 1 tsp Sichuan chilli oil", " 1 spring onion, finely chopped", " 1 small handful ground, fried dry baby shrimp", " 1 pinch ground toasted Sichuan peppercorns"]}