{"title": "Black bean and brown rice bowl with poached eggs", "url": "http://www.bbc.co.uk/food/recipes/black_bean_and_smoke_29105", "img": "http://ichef.bbci.co.uk/food/ic/food_16x9_608/recipes/black_bean_and_smoke_29105_16x9.jpg", "description": "\n    The simple addition of poached eggs takes this dish from zero to hero in no time. You can even use leftover or pre-cooked rice.\n", "prep time": "less than 30 mins", "cook time": "30 mins to 1 hour", "serves": "Serves 2", "ingredients": [" 110g/3\u00c2\u00bdoz brown rice, rinsed", " 1 tbsp olive oil", " 1 x 400g tin black beans, drained and rinsed ", " 2 tsp smoked paprika", " 1 tsp white wine vinegar", " 2 free-range eggs", " 50g/2oz spinach ", " 1 avocado, halved and sliced", " 60g/2oz feta, crumbled", " 1 lemon, juice only", " sea salt and freshly ground black pepper"]}