{"title": "Cranberry mincemeat", "url": "http://www.bbc.co.uk/food/recipes/cranberrymincemeat_73340", "img": null, "description": null, "prep time": "less than 30 mins", "cook time": "10 to 30 mins", "serves": "Makes 1.2kg -enough for 24 pies", "ingredients": [" 100g/3\u00bdoz butter", " 200g/7oz soft dark brown sugar e.g. unrefined muscovado", " 250ml/9fl oz orange juice", " 2 tsp ground mixed spice", " \u00bd tsp ground cinnamon", " \u00bd tsp ginger", " pinch of grated nutmeg", " 250g/9oz Bramley apples", " 200g/7oz sultanas", " 200g/7oz currants", " 100g/3\u00bdoz dried cranberries or raisins", " 200g/7oz mixed candied peel, finely chopped", " 1 tbsp grated orange zest", " 150ml brandy, cognac, rum or whisky"]}