{"title": "John Dory, mousseron mushrooms, broad beans and wild strawberries", "url": "http://www.bbc.co.uk/food/recipes/john_dory_mousseron_78446", "img": null, "description": "\n    Wild strawberries are smaller and have a more intense flavour than regular ones, if they grow freely in your garden this is a lovely way to serve them. \n", "prep time": "less than 30 mins", "cook time": "10 to 30 mins", "serves": "Serves 4", "ingredients": [" 2 punnets wild strawberries ", " 1-2 tbsp olive oil ", " 1 puntarella (Italian chicory), finely chopped ", " salt and pepper ", " 1.5kg/3lb 5oz small broad beans, podded ", " knob of butter, for frying", " drizzle olive oil, for frying ", " 1 shallot, finely chopped ", " 300g/10\u00bdoz mousseron mushrooms, cleaned ", " salt and pepper ", " 4 John Dory fillets (about 200g/7oz each) ", " 1 egg yolk, beaten ", " 200g/7oz dried white breadcrumbs", " knob of butter, for frying", " drizzle olive oil, for frying", " 1 sprig thyme ", " 1 garlic clove, squashed and left whole", " salt and pepper ", " Lemon balm cress, lambs lettuce cress, bergamot cress, apple blossom cress, to garnish"]}