{"title": "Red mullet with Thai pur\u00e9e, fennel, dill and lime salad with tomato ketchup sauce", "url": "http://www.bbc.co.uk/food/recipes/red_mullet_with_thai_05964", "img": null, "description": "\n    Fried red mullet with finely sliced fennel is a great combination, here served with richly flavoured sauces and oils.\n", "prep time": "overnight", "cook time": "over 2 hours", "serves": "Serves 4", "ingredients": [" 60g/2\u00bcoz butter", " 7g/\u00bcoz lemongrass, finely chopped ", " 4g garlic, crushed", " 4g ginger, peeled and chopped", " 2g madras curry powder ", " 7g/\u00bcoz saffron", " 1 lime, juice only", " 1 white onion finely chopped", " 150ml/5fl oz fish stock", " 30g/1oz lime peel, chopped ", " 150g/5\u00bdoz olive oil", " 30g/1oz basil leaves ", " 300ml/10\u00bdfl oz extra virgin olive oil", " 60g/2\u00bcoz unsalted butter", " 3g fennel seeds, toasted then chopped", " 3g finely chopped shallot", " 50g/1\u00beoz tomato ketchup", " 150ml/5fl oz lime oil ", " 50ml/2fl oz lime juice", " pinch salt ", " pinch ground white pepper ", " 1 sprig fresh lemon thyme", " 2 fennel bulbs, thinly sliced", " iced water", " 1 tsp chopped dill", " salt and freshly ground black pepper", " 2 tbsp olive oil", " 4 x red mullet fillets, 80-90g/3oz each, pin boned", " salt and freshly ground black pepper", " 1 lime, juice only", " micro basil leaves ", " 1 tsp finely chopped fennel seeds, toasted"]}