{"title": "style spicy bean curd", "url": "http://www.bbc.co.uk/food/recipes/steamed_fish_cantonese_58174", "img": null, "description": "\n    Ken Hom's steamed fish and spicy tofu is healthy and tasty. \n", "prep time": "30 mins to 1 hour", "cook time": "10 to 30 mins", "serves": "Serves 4", "ingredients": [" 450g/1lb lemon sole fillets, skin removed", " 1 tsp coarse sea salt", " 1\u00bd tbsp finely shredded fresh root ginger", " 3 tbsp finely shredded spring onions", " 2 tbsp dark soy sauce", " 1 tbsp groundnut oil ", " 2 tsp sesame oil", " 1 tbsp groundnut oil ", " 1 tbsp ready-made whole yellow bean sauce", " 1 tbsp dark soy sauce", " \u00bd tsp salt, or to taste", " 1 tsp red chilli powder ", " 170ml/6fl oz hot chicken or vegetable stock", " 450g/1 lb fresh soft bean curd (tofu), cut into 3.5cm/1\u00bdin cubes", " 2 tbsp coarsely chopped garlic", " 2 tsp cornflour, mixed to a paste with 1 tbsp water", " fresh coriander sprigs", " 1 tsp Sichuan peppercorns, roasted and finely ground"]}