{"title": "Julie's bread and butter pudding", "url": "http://www.bbc.co.uk/food/recipes/julies_bread_and_butter_14219", "img": null, "description": "\n    If you have to feed a lot of people, this is a quick and simple pudding . Make it in several dishes if you don't have one big enough.\n", "prep time": "less than 30 mins", "cook time": "30 mins to 1 hour", "serves": "Serves 36", "ingredients": [" 36 slices white bread ", " 300g/10\u00bdoz butter, softened, plus extra for greasing", " 175g/6oz mixed dried fruit ", " 175g/6oz sultanas ", " 300g/10\u00bdoz caster sugar ", " 12 eggs ", " 3.4 litres/6 pints milk "]}