{"title": "style chocolate brownies", "url": "http://www.bbc.co.uk/food/recipes/americanstylechocola_88413", "img": null, "description": null, "prep time": "less than 30 mins", "cook time": "10 to 30 mins", "serves": "Serves 6", "ingredients": [" 180g/6\u00bcoz dark chocolate, broken into squares", " 150g/5\u00bcoz unsalted butter, plus extra for greasing ", " 120g/4\u00bcoz caster sugar ", " 2 free-range eggs, lightly beaten", " 50g/1\u00beoz plain flour ", " \u00bd tsp baking powder", " 1 Snickers bar or similar confectionery", " 140ml/5fl oz double cream", " 1 tbsp golden syrup", " 140g/5oz dark chocolate, broken into squares", " 25g/1oz butter", " vanilla ice cream"]}