{"title": "Roasted rib of beef with horseradish Yorkshire pudding and leek gratin", "url": "http://www.bbc.co.uk/food/recipes/roastedribofbeefwith_87818", "img": null, "description": null, "prep time": "overnight", "cook time": "1 to 2 hours", "serves": "Serves 6-8", "ingredients": [" 4 kg/8lb 8oz fore-rib of 28-day aged beef, on the bone", " salt and freshly ground black pepper ", " dash olive oil", " 225g/8oz plain flour", " salt and freshly ground black pepper ", " 8 free-range eggs", " 600ml/1 pint 1fl oz milk", " 4 tbsp grated fresh horseradish ", " 50g/2oz beef dripping or lard", " 25g/1oz butter", " 2 tbsp olive oil", " 4 large leeks, finely sliced into rings", " 300ml/11fl oz white wine", " 125ml/4\u00c2\u00bdfl oz double cream", " salt and freshly ground black pepper ", " 110g/4oz mature cheddar cheese"]}